LICENSE.md
mkdocs_alabaster/404.html
mkdocs_alabaster/__init__.py
mkdocs_alabaster/config.html
mkdocs_alabaster/css/alabaster-overrides.css
mkdocs_alabaster/css/alabaster.css
mkdocs_alabaster/css/basic.css
mkdocs_alabaster/inc/homepage_nav.html
mkdocs_alabaster/js/theme.js
mkdocs_alabaster/main.html
mkdocs_alabaster/mkdocs_theme.yml
mkdocs_alabaster/search.html
mkdocs_alabaster/sidebars/about.html
mkdocs_alabaster/sidebars/navigation.html
mkdocs_alabaster/sidebars/related.html
mkdocs_alabaster/sidebars/search.html
mkdocs_alabaster/sidebars/toc.html
mkdocs_alabaster-0.8.0.dist-info/entry_points.txt
mkdocs_alabaster-0.8.0.dist-info/LICENSE.md
mkdocs_alabaster-0.8.0.dist-info/WHEEL
mkdocs_alabaster-0.8.0.dist-info/METADATA
mkdocs_alabaster-0.8.0.dist-info/RECORD
