Metadata-Version: 2.1
Name: mkdocs-alabaster
Version: 0.8.0
Summary: Alabaster port for MkDocs
Author: Alexander Pushkov
Author-email: alexander@notpushk.in
Requires-Python: >=3.6,<4.0
Classifier: Programming Language :: Python :: 3
Classifier: Programming Language :: Python :: 3.6
Classifier: Programming Language :: Python :: 3.7
Requires-Dist: mkdocs (>=1.0,<2.0)
